[{"type":"directory","name": ".","contents":[
    {"type":"file","name":"index.html","size":0},
    {"type":"file","name":"index.json","size":170708},
    {"type":"directory","name":"snip","size":4096,"contents":[
      {"type":"directory","name":"b","size":4096,"contents":[
        {"type":"directory","name":"base64-js","size":4096,"contents":[
          {"type":"directory","name":"1.0.2","size":4096,"contents":[
            {"type":"file","name":"core.html","size":86},
            {"type":"file","name":"core.mod.html","size":46},
            {"type":"file","name":"min.html","size":90},
            {"type":"file","name":"min.mod.html","size":46}
          ]},
          {"type":"directory","name":"latest","size":4096,"contents":[
            {"type":"file","name":"core.html","size":86},
            {"type":"file","name":"core.mod.html","size":46},
            {"type":"file","name":"min.html","size":90},
            {"type":"file","name":"min.mod.html","size":46}
          ]}
        ]},
        {"type":"directory","name":"bitcoinjs-lib","size":4096,"contents":[
          {"type":"directory","name":"0.2.0-1","size":4096,"contents":[
            {"type":"file","name":"min.html","size":102},
            {"type":"file","name":"min.mod.html","size":52}
          ]},
          {"type":"directory","name":"latest","size":4096,"contents":[
            {"type":"file","name":"min.html","size":102},
            {"type":"file","name":"min.mod.html","size":52}
          ]}
        ]},
        {"type":"directory","name":"bootstrap","size":4096,"contents":[
          {"type":"directory","name":"3.0.0","size":4096,"contents":[
            {"type":"file","name":"core.html","size":88},
            {"type":"file","name":"core.mod.html","size":46},
            {"type":"file","name":"min.html","size":92},
            {"type":"file","name":"min.mod.html","size":46}
          ]},
          {"type":"directory","name":"3.0.1","size":4096,"contents":[
            {"type":"file","name":"core.html","size":103},
            {"type":"file","name":"core.mod.html","size":46},
            {"type":"file","name":"min.html","size":107},
            {"type":"file","name":"min.mod.html","size":46}
          ]},
          {"type":"directory","name":"3.1.0","size":4096,"contents":[
            {"type":"file","name":"core.html","size":103},
            {"type":"file","name":"core.mod.html","size":46},
            {"type":"file","name":"min.html","size":107},
            {"type":"file","name":"min.mod.html","size":46}
          ]},
          {"type":"directory","name":"3.3.7","size":4096,"contents":[
            {"type":"file","name":"core.html","size":103},
            {"type":"file","name":"core.mod.html","size":46},
            {"type":"file","name":"min.html","size":107},
            {"type":"file","name":"min.mod.html","size":46}
          ]},
          {"type":"directory","name":"3.4.1","size":4096,"contents":[
            {"type":"file","name":"core.html","size":103},
            {"type":"file","name":"core.mod.html","size":46},
            {"type":"file","name":"min.html","size":107},
            {"type":"file","name":"min.mod.html","size":46}
          ]},
          {"type":"directory","name":"4.0.0","size":4096,"contents":[
            {"type":"file","name":"core.html","size":88},
            {"type":"file","name":"core.mod.html","size":46},
            {"type":"file","name":"min.html","size":92},
            {"type":"file","name":"min.mod.html","size":46}
          ]},
          {"type":"directory","name":"4.1.0","size":4096,"contents":[
            {"type":"file","name":"core.html","size":91},
            {"type":"file","name":"core.mod.html","size":46},
            {"type":"file","name":"min.html","size":95},
            {"type":"file","name":"min.mod.html","size":46}
          ]},
          {"type":"directory","name":"4.1.1","size":4096,"contents":[
            {"type":"file","name":"core.html","size":88},
            {"type":"file","name":"core.mod.html","size":46},
            {"type":"file","name":"min.html","size":92},
            {"type":"file","name":"min.mod.html","size":46}
          ]},
          {"type":"directory","name":"4.2.0","size":4096,"contents":[
            {"type":"file","name":"core.html","size":91},
            {"type":"file","name":"core.mod.html","size":46},
            {"type":"file","name":"min.html","size":95},
            {"type":"file","name":"min.mod.html","size":46}
          ]},
          {"type":"directory","name":"4.2.1","size":4096,"contents":[
            {"type":"file","name":"core.html","size":91},
            {"type":"file","name":"core.mod.html","size":46},
            {"type":"file","name":"min.html","size":95},
            {"type":"file","name":"min.mod.html","size":46}
          ]},
          {"type":"directory","name":"4.3.0","size":4096,"contents":[
            {"type":"file","name":"core.html","size":91},
            {"type":"file","name":"core.mod.html","size":46},
            {"type":"file","name":"min.html","size":95},
            {"type":"file","name":"min.mod.html","size":46}
          ]},
          {"type":"directory","name":"4.3.1","size":4096,"contents":[
            {"type":"file","name":"core.html","size":91},
            {"type":"file","name":"core.mod.html","size":46},
            {"type":"file","name":"min.html","size":95},
            {"type":"file","name":"min.mod.html","size":46}
          ]},
          {"type":"directory","name":"latest","size":4096,"contents":[
            {"type":"file","name":"core.html","size":91},
            {"type":"file","name":"core.mod.html","size":46},
            {"type":"file","name":"min.html","size":95},
            {"type":"file","name":"min.mod.html","size":46}
          ]}
        ]}
      ]},
      {"type":"directory","name":"c","size":4096,"contents":[
        {"type":"directory","name":"clipboard-js","size":4096,"contents":[
          {"type":"directory","name":"2.0.4","size":4096,"contents":[
            {"type":"file","name":"core.html","size":95},
            {"type":"file","name":"core.mod.html","size":46},
            {"type":"file","name":"min.html","size":99},
            {"type":"file","name":"min.mod.html","size":46}
          ]},
          {"type":"directory","name":"latest","size":4096,"contents":[
            {"type":"file","name":"core.html","size":95},
            {"type":"file","name":"core.mod.html","size":46},
            {"type":"file","name":"min.html","size":99},
            {"type":"file","name":"min.mod.html","size":46}
          ]}
        ]},
        {"type":"directory","name":"counterup","size":4096,"contents":[
          {"type":"directory","name":"1.0.0","size":4096,"contents":[
            {"type":"file","name":"core.html","size":100},
            {"type":"file","name":"core.mod.html","size":46},
            {"type":"file","name":"min.html","size":104},
            {"type":"file","name":"min.mod.html","size":46}
          ]},
          {"type":"directory","name":"latest","size":4096,"contents":[
            {"type":"file","name":"core.html","size":100},
            {"type":"file","name":"core.mod.html","size":46},
            {"type":"file","name":"min.html","size":104},
            {"type":"file","name":"min.mod.html","size":46}
          ]}
        ]},
        {"type":"directory","name":"crypto-js","size":4096,"contents":[
          {"type":"directory","name":"3.1.9-1","size":4096,"contents":[
            {"type":"file","name":"core.html","size":94},
            {"type":"file","name":"core.mod.html","size":46},
            {"type":"file","name":"min.html","size":98},
            {"type":"file","name":"min.mod.html","size":46}
          ]},
          {"type":"directory","name":"latest","size":4096,"contents":[
            {"type":"file","name":"core.html","size":94},
            {"type":"file","name":"core.mod.html","size":46},
            {"type":"file","name":"min.html","size":98},
            {"type":"file","name":"min.mod.html","size":46}
          ]}
        ]}
      ]},
      {"type":"directory","name":"d","size":4096,"contents":[
        {"type":"directory","name":"d3","size":4096,"contents":[
          {"type":"directory","name":"5.11.0","size":4096,"contents":[
            {"type":"file","name":"core.html","size":79},
            {"type":"file","name":"core.mod.html","size":46},
            {"type":"file","name":"min.html","size":83},
            {"type":"file","name":"min.mod.html","size":46}
          ]},
          {"type":"directory","name":"latest","size":4096,"contents":[
            {"type":"file","name":"core.html","size":79},
            {"type":"file","name":"core.mod.html","size":46},
            {"type":"file","name":"min.html","size":83},
            {"type":"file","name":"min.mod.html","size":46}
          ]}
        ]},
        {"type":"directory","name":"d3-geo-projection","size":4096,"contents":[
          {"type":"directory","name":"2.4.0","size":4096,"contents":[
            {"type":"file","name":"core.html","size":108},
            {"type":"file","name":"core.mod.html","size":46},
            {"type":"file","name":"min.html","size":112},
            {"type":"file","name":"min.mod.html","size":46}
          ]},
          {"type":"directory","name":"latest","size":4096,"contents":[
            {"type":"file","name":"core.html","size":108},
            {"type":"file","name":"core.mod.html","size":46},
            {"type":"file","name":"min.html","size":112},
            {"type":"file","name":"min.mod.html","size":46}
          ]}
        ]},
        {"type":"directory","name":"datatables","size":4096,"contents":[
          {"type":"directory","name":"1.10.19","size":4096,"contents":[
            {"type":"file","name":"bootstrap4.html","size":110},
            {"type":"file","name":"bootstrap4.min.html","size":114},
            {"type":"file","name":"bootstrap4.min.mod.html","size":46},
            {"type":"file","name":"bootstrap4.mod.html","size":46},
            {"type":"file","name":"bootstrap.html","size":109},
            {"type":"file","name":"bootstrap.min.html","size":113},
            {"type":"file","name":"bootstrap.min.mod.html","size":46},
            {"type":"file","name":"bootstrap.mod.html","size":46},
            {"type":"file","name":"core.html","size":110},
            {"type":"file","name":"core.mod.html","size":46},
            {"type":"file","name":"foundation.html","size":110},
            {"type":"file","name":"foundation.min.html","size":114},
            {"type":"file","name":"foundation.min.mod.html","size":46},
            {"type":"file","name":"foundation.mod.html","size":46},
            {"type":"file","name":"jquery.dataTables.html","size":106},
            {"type":"file","name":"jquery.dataTables.min.html","size":110},
            {"type":"file","name":"jquery.dataTables.min.mod.html","size":46},
            {"type":"file","name":"jquery.dataTables.mod.html","size":46},
            {"type":"file","name":"jqueryui.html","size":108},
            {"type":"file","name":"jqueryui.min.html","size":112},
            {"type":"file","name":"jqueryui.min.mod.html","size":46},
            {"type":"file","name":"jqueryui.mod.html","size":46},
            {"type":"file","name":"material.html","size":108},
            {"type":"file","name":"material.min.html","size":112},
            {"type":"file","name":"material.min.mod.html","size":46},
            {"type":"file","name":"material.mod.html","size":46},
            {"type":"file","name":"min.html","size":114},
            {"type":"file","name":"min.mod.html","size":46},
            {"type":"file","name":"semanticui.html","size":110},
            {"type":"file","name":"semanticui.min.html","size":114},
            {"type":"file","name":"semanticui.min.mod.html","size":46},
            {"type":"file","name":"semanticui.mod.html","size":46},
            {"type":"file","name":"uikit.html","size":105},
            {"type":"file","name":"uikit.min.html","size":109},
            {"type":"file","name":"uikit.min.mod.html","size":46},
            {"type":"file","name":"uikit.mod.html","size":46}
          ]},
          {"type":"directory","name":"latest","size":4096,"contents":[
            {"type":"file","name":"bootstrap4.html","size":110},
            {"type":"file","name":"bootstrap4.min.html","size":114},
            {"type":"file","name":"bootstrap4.min.mod.html","size":46},
            {"type":"file","name":"bootstrap4.mod.html","size":46},
            {"type":"file","name":"bootstrap.html","size":109},
            {"type":"file","name":"bootstrap.min.html","size":113},
            {"type":"file","name":"bootstrap.min.mod.html","size":46},
            {"type":"file","name":"bootstrap.mod.html","size":46},
            {"type":"file","name":"core.html","size":110},
            {"type":"file","name":"core.mod.html","size":46},
            {"type":"file","name":"foundation.html","size":110},
            {"type":"file","name":"foundation.min.html","size":114},
            {"type":"file","name":"foundation.min.mod.html","size":46},
            {"type":"file","name":"foundation.mod.html","size":46},
            {"type":"file","name":"jquery.dataTables.html","size":106},
            {"type":"file","name":"jquery.dataTables.min.html","size":110},
            {"type":"file","name":"jquery.dataTables.min.mod.html","size":46},
            {"type":"file","name":"jquery.dataTables.mod.html","size":46},
            {"type":"file","name":"jqueryui.html","size":108},
            {"type":"file","name":"jqueryui.min.html","size":112},
            {"type":"file","name":"jqueryui.min.mod.html","size":46},
            {"type":"file","name":"jqueryui.mod.html","size":46},
            {"type":"file","name":"material.html","size":108},
            {"type":"file","name":"material.min.html","size":112},
            {"type":"file","name":"material.min.mod.html","size":46},
            {"type":"file","name":"material.mod.html","size":46},
            {"type":"file","name":"min.html","size":114},
            {"type":"file","name":"min.mod.html","size":46},
            {"type":"file","name":"semanticui.html","size":110},
            {"type":"file","name":"semanticui.min.html","size":114},
            {"type":"file","name":"semanticui.min.mod.html","size":46},
            {"type":"file","name":"semanticui.mod.html","size":46},
            {"type":"file","name":"uikit.html","size":105},
            {"type":"file","name":"uikit.min.html","size":109},
            {"type":"file","name":"uikit.min.mod.html","size":46},
            {"type":"file","name":"uikit.mod.html","size":46}
          ]}
        ]},
        {"type":"directory","name":"dygraph","size":4096,"contents":[
          {"type":"directory","name":"2.1.0","size":4096,"contents":[
            {"type":"file","name":"core.html","size":88},
            {"type":"file","name":"core.mod.html","size":46},
            {"type":"file","name":"min.html","size":92},
            {"type":"file","name":"min.mod.html","size":46}
          ]},
          {"type":"directory","name":"latest","size":4096,"contents":[
            {"type":"file","name":"core.html","size":88},
            {"type":"file","name":"core.mod.html","size":46},
            {"type":"file","name":"min.html","size":92},
            {"type":"file","name":"min.mod.html","size":46}
          ]}
        ]},
        {"type":"directory","name":"dynamics-js","size":4096,"contents":[
          {"type":"directory","name":"1.1.5","size":4096,"contents":[
            {"type":"file","name":"core.html","size":93},
            {"type":"file","name":"core.mod.html","size":46},
            {"type":"file","name":"min.html","size":97},
            {"type":"file","name":"min.mod.html","size":46}
          ]},
          {"type":"directory","name":"latest","size":4096,"contents":[
            {"type":"file","name":"core.html","size":93},
            {"type":"file","name":"core.mod.html","size":46},
            {"type":"file","name":"min.html","size":97},
            {"type":"file","name":"min.mod.html","size":46}
          ]}
        ]}
      ]},
      {"type":"file","name":"index.html","size":96624},
      {"type":"directory","name":"j","size":4096,"contents":[
        {"type":"directory","name":"jquery","size":4096,"contents":[
          {"type":"directory","name":"3.3.0","size":4096,"contents":[
            {"type":"file","name":"core.html","size":64},
            {"type":"file","name":"core.mod.html","size":46},
            {"type":"file","name":"min.html","size":68},
            {"type":"file","name":"min.mod.html","size":46},
            {"type":"file","name":"slim.html","size":69},
            {"type":"file","name":"slim.min.html","size":73},
            {"type":"file","name":"slim.min.mod.html","size":46},
            {"type":"file","name":"slim.mod.html","size":46}
          ]},
          {"type":"directory","name":"3.3.1","size":4096,"contents":[
            {"type":"file","name":"core.html","size":64},
            {"type":"file","name":"core.mod.html","size":46},
            {"type":"file","name":"min.html","size":68},
            {"type":"file","name":"min.mod.html","size":46},
            {"type":"file","name":"slim.html","size":69},
            {"type":"file","name":"slim.min.html","size":73},
            {"type":"file","name":"slim.min.mod.html","size":46},
            {"type":"file","name":"slim.mod.html","size":46}
          ]},
          {"type":"directory","name":"latest","size":4096,"contents":[
            {"type":"file","name":"core.html","size":64},
            {"type":"file","name":"core.mod.html","size":46},
            {"type":"file","name":"min.html","size":68},
            {"type":"file","name":"min.mod.html","size":46},
            {"type":"file","name":"slim.html","size":69},
            {"type":"file","name":"slim.min.html","size":73},
            {"type":"file","name":"slim.min.mod.html","size":46},
            {"type":"file","name":"slim.mod.html","size":46}
          ]}
        ]},
        {"type":"directory","name":"jquery-imagesloaded","size":4096,"contents":[
          {"type":"directory","name":"4.1.4","size":4096,"contents":[
            {"type":"file","name":"core.html","size":105},
            {"type":"file","name":"core.mod.html","size":46},
            {"type":"file","name":"min.html","size":109},
            {"type":"file","name":"min.mod.html","size":46},
            {"type":"file","name":"pkgd.html","size":110},
            {"type":"file","name":"pkgd.min.html","size":114},
            {"type":"file","name":"pkgd.min.mod.html","size":46},
            {"type":"file","name":"pkgd.mod.html","size":46}
          ]},
          {"type":"directory","name":"latest","size":4096,"contents":[
            {"type":"file","name":"core.html","size":105},
            {"type":"file","name":"core.mod.html","size":46},
            {"type":"file","name":"min.html","size":109},
            {"type":"file","name":"min.mod.html","size":46},
            {"type":"file","name":"pkgd.html","size":110},
            {"type":"file","name":"pkgd.min.html","size":114},
            {"type":"file","name":"pkgd.min.mod.html","size":46},
            {"type":"file","name":"pkgd.mod.html","size":46}
          ]}
        ]},
        {"type":"directory","name":"jquery-magnific-popup","size":4096,"contents":[
          {"type":"directory","name":"1.1.0","size":4096,"contents":[
            {"type":"file","name":"core.html","size":112},
            {"type":"file","name":"core.mod.html","size":46},
            {"type":"file","name":"min.html","size":116},
            {"type":"file","name":"min.mod.html","size":46}
          ]},
          {"type":"directory","name":"latest","size":4096,"contents":[
            {"type":"file","name":"core.html","size":112},
            {"type":"file","name":"core.mod.html","size":46},
            {"type":"file","name":"min.html","size":116},
            {"type":"file","name":"min.mod.html","size":46}
          ]}
        ]},
        {"type":"directory","name":"jquery-metismenu","size":4096,"contents":[
          {"type":"directory","name":"3.0.4","size":4096,"contents":[
            {"type":"file","name":"core.html","size":92},
            {"type":"file","name":"core.mod.html","size":46},
            {"type":"file","name":"min.html","size":96},
            {"type":"file","name":"min.mod.html","size":46}
          ]},
          {"type":"directory","name":"latest","size":4096,"contents":[
            {"type":"file","name":"core.html","size":92},
            {"type":"file","name":"core.mod.html","size":46},
            {"type":"file","name":"min.html","size":96},
            {"type":"file","name":"min.mod.html","size":46}
          ]}
        ]},
        {"type":"directory","name":"jquery-slimscroll","size":4096,"contents":[
          {"type":"directory","name":"1.3.8","size":4096,"contents":[
            {"type":"file","name":"core.html","size":108},
            {"type":"file","name":"core.mod.html","size":46},
            {"type":"file","name":"min.html","size":112},
            {"type":"file","name":"min.mod.html","size":46}
          ]},
          {"type":"directory","name":"latest","size":4096,"contents":[
            {"type":"file","name":"core.html","size":108},
            {"type":"file","name":"core.mod.html","size":46},
            {"type":"file","name":"min.html","size":112},
            {"type":"file","name":"min.mod.html","size":46}
          ]}
        ]},
        {"type":"directory","name":"jquery-ui","size":4096,"contents":[
          {"type":"directory","name":"1.12.1","size":4096,"contents":[
            {"type":"file","name":"core.html","size":92},
            {"type":"file","name":"core.mod.html","size":46},
            {"type":"file","name":"min.html","size":96},
            {"type":"file","name":"min.mod.html","size":46}
          ]},
          {"type":"directory","name":"latest","size":4096,"contents":[
            {"type":"file","name":"core.html","size":92},
            {"type":"file","name":"core.mod.html","size":46},
            {"type":"file","name":"min.html","size":96},
            {"type":"file","name":"min.mod.html","size":46}
          ]}
        ]},
        {"type":"directory","name":"json2html","size":4096,"contents":[
          {"type":"directory","name":"1.3.0","size":4096,"contents":[
            {"type":"file","name":"core.html","size":92},
            {"type":"file","name":"core.mod.html","size":46},
            {"type":"file","name":"min.html","size":96},
            {"type":"file","name":"min.mod.html","size":46}
          ]},
          {"type":"directory","name":"latest","size":4096,"contents":[
            {"type":"file","name":"core.html","size":92},
            {"type":"file","name":"core.mod.html","size":46},
            {"type":"file","name":"min.html","size":96},
            {"type":"file","name":"min.mod.html","size":46}
          ]}
        ]},
        {"type":"directory","name":"jszip","size":4096,"contents":[
          {"type":"directory","name":"3.2.2","size":4096,"contents":[
            {"type":"file","name":"core.html","size":84},
            {"type":"file","name":"core.mod.html","size":46},
            {"type":"file","name":"min.html","size":88},
            {"type":"file","name":"min.mod.html","size":46}
          ]},
          {"type":"directory","name":"latest","size":4096,"contents":[
            {"type":"file","name":"core.html","size":84},
            {"type":"file","name":"core.mod.html","size":46},
            {"type":"file","name":"min.html","size":88},
            {"type":"file","name":"min.mod.html","size":46}
          ]}
        ]}
      ]},
      {"type":"directory","name":"o","size":4096,"contents":[
        {"type":"directory","name":"openpgp-js","size":4096,"contents":[
          {"type":"directory","name":"4.6.0","size":4096,"contents":[
            {"type":"file","name":"compat.html","size":95},
            {"type":"file","name":"compat.min.html","size":99},
            {"type":"file","name":"compat.min.mod.html","size":46},
            {"type":"file","name":"compat.mod.html","size":46},
            {"type":"file","name":"compat.worker.html","size":102},
            {"type":"file","name":"compat.worker.min.html","size":106},
            {"type":"file","name":"compat.worker.min.mod.html","size":46},
            {"type":"file","name":"compat.worker.mod.html","size":46},
            {"type":"file","name":"core.html","size":88},
            {"type":"file","name":"core.mod.html","size":46},
            {"type":"file","name":"min.html","size":92},
            {"type":"file","name":"min.mod.html","size":46},
            {"type":"file","name":"worker.html","size":95},
            {"type":"file","name":"worker.min.html","size":99},
            {"type":"file","name":"worker.min.mod.html","size":46},
            {"type":"file","name":"worker.mod.html","size":46}
          ]},
          {"type":"directory","name":"latest","size":4096,"contents":[
            {"type":"file","name":"compat.html","size":95},
            {"type":"file","name":"compat.min.html","size":99},
            {"type":"file","name":"compat.min.mod.html","size":46},
            {"type":"file","name":"compat.mod.html","size":46},
            {"type":"file","name":"compat.worker.html","size":102},
            {"type":"file","name":"compat.worker.min.html","size":106},
            {"type":"file","name":"compat.worker.min.mod.html","size":46},
            {"type":"file","name":"compat.worker.mod.html","size":46},
            {"type":"file","name":"core.html","size":88},
            {"type":"file","name":"core.mod.html","size":46},
            {"type":"file","name":"min.html","size":92},
            {"type":"file","name":"min.mod.html","size":46},
            {"type":"file","name":"worker.html","size":95},
            {"type":"file","name":"worker.min.html","size":99},
            {"type":"file","name":"worker.min.mod.html","size":46},
            {"type":"file","name":"worker.mod.html","size":46}
          ]}
        ]}
      ]},
      {"type":"directory","name":"p","size":4096,"contents":[
        {"type":"directory","name":"parallax-js","size":4096,"contents":[
          {"type":"directory","name":"3.1.0","size":4096,"contents":[
            {"type":"file","name":"core.html","size":90},
            {"type":"file","name":"core.mod.html","size":46},
            {"type":"file","name":"min.html","size":94},
            {"type":"file","name":"min.mod.html","size":46}
          ]},
          {"type":"directory","name":"latest","size":4096,"contents":[
            {"type":"file","name":"core.html","size":90},
            {"type":"file","name":"core.mod.html","size":46},
            {"type":"file","name":"min.html","size":94},
            {"type":"file","name":"min.mod.html","size":46}
          ]}
        ]},
        {"type":"directory","name":"popper","size":4096,"contents":[
          {"type":"directory","name":"1.14.6","size":4096,"contents":[
            {"type":"file","name":"core.html","size":94},
            {"type":"file","name":"core.mod.html","size":46},
            {"type":"file","name":"min.html","size":98},
            {"type":"file","name":"min.mod.html","size":46}
          ]},
          {"type":"directory","name":"1.14.7","size":4096,"contents":[
            {"type":"file","name":"core.html","size":94},
            {"type":"file","name":"core.mod.html","size":46},
            {"type":"file","name":"min.html","size":98},
            {"type":"file","name":"min.mod.html","size":46}
          ]},
          {"type":"directory","name":"latest","size":4096,"contents":[
            {"type":"file","name":"core.html","size":94},
            {"type":"file","name":"core.mod.html","size":46},
            {"type":"file","name":"min.html","size":98},
            {"type":"file","name":"min.mod.html","size":46}
          ]}
        ]},
        {"type":"directory","name":"pouchdb","size":4096,"contents":[
          {"type":"directory","name":"7.1.1","size":4096,"contents":[
            {"type":"file","name":"core.html","size":88},
            {"type":"file","name":"core.mod.html","size":46},
            {"type":"file","name":"min.html","size":92},
            {"type":"file","name":"min.mod.html","size":46}
          ]},
          {"type":"directory","name":"latest","size":4096,"contents":[
            {"type":"file","name":"core.html","size":88},
            {"type":"file","name":"core.mod.html","size":46},
            {"type":"file","name":"min.html","size":92},
            {"type":"file","name":"min.mod.html","size":46}
          ]}
        ]}
      ]},
      {"type":"directory","name":"s","size":4096,"contents":[
        {"type":"directory","name":"sizzle-js","size":4096,"contents":[
          {"type":"directory","name":"2.3.4","size":4096,"contents":[
            {"type":"file","name":"core.html","size":86},
            {"type":"file","name":"core.mod.html","size":46},
            {"type":"file","name":"min.html","size":90},
            {"type":"file","name":"min.mod.html","size":46}
          ]},
          {"type":"directory","name":"latest","size":4096,"contents":[
            {"type":"file","name":"core.html","size":86},
            {"type":"file","name":"core.mod.html","size":46},
            {"type":"file","name":"min.html","size":90},
            {"type":"file","name":"min.mod.html","size":46}
          ]}
        ]},
        {"type":"directory","name":"slick","size":4096,"contents":[
          {"type":"directory","name":"1.9.0","size":4096,"contents":[
            {"type":"file","name":"core.html","size":93},
            {"type":"file","name":"core.mod.html","size":46},
            {"type":"file","name":"min.html","size":97},
            {"type":"file","name":"min.mod.html","size":46}
          ]},
          {"type":"directory","name":"latest","size":4096,"contents":[
            {"type":"file","name":"core.html","size":93},
            {"type":"file","name":"core.mod.html","size":46},
            {"type":"file","name":"min.html","size":97},
            {"type":"file","name":"min.mod.html","size":46}
          ]}
        ]},
        {"type":"directory","name":"socket-io","size":4096,"contents":[
          {"type":"directory","name":"2.2.0","size":4096,"contents":[
            {"type":"file","name":"core.html","size":92},
            {"type":"file","name":"core.mod.html","size":46},
            {"type":"file","name":"dev.html","size":96},
            {"type":"file","name":"dev.mod.html","size":46},
            {"type":"file","name":"slim.dev.html","size":101},
            {"type":"file","name":"slim.dev.mod.html","size":46},
            {"type":"file","name":"slim.html","size":97},
            {"type":"file","name":"slim.mod.html","size":46}
          ]},
          {"type":"directory","name":"latest","size":4096,"contents":[
            {"type":"file","name":"core.html","size":92},
            {"type":"file","name":"core.mod.html","size":46},
            {"type":"file","name":"dev.html","size":96},
            {"type":"file","name":"dev.mod.html","size":46},
            {"type":"file","name":"slim.dev.html","size":101},
            {"type":"file","name":"slim.dev.mod.html","size":46},
            {"type":"file","name":"slim.html","size":97},
            {"type":"file","name":"slim.mod.html","size":46}
          ]}
        ]}
      ]},
      {"type":"directory","name":"t","size":4096,"contents":[
        {"type":"directory","name":"three-js","size":4096,"contents":[
          {"type":"directory","name":"108","size":4096,"contents":[
            {"type":"file","name":"core.html","size":85},
            {"type":"file","name":"core.mod.html","size":46},
            {"type":"file","name":"min.html","size":89},
            {"type":"file","name":"min.mod.html","size":46},
            {"type":"file","name":"module.html","size":92},
            {"type":"file","name":"module.mod.html","size":46}
          ]},
          {"type":"directory","name":"latest","size":4096,"contents":[
            {"type":"file","name":"core.html","size":85},
            {"type":"file","name":"core.mod.html","size":46},
            {"type":"file","name":"min.html","size":89},
            {"type":"file","name":"min.mod.html","size":46},
            {"type":"file","name":"module.html","size":92},
            {"type":"file","name":"module.mod.html","size":46}
          ]}
        ]},
        {"type":"directory","name":"toastr-js","size":4096,"contents":[
          {"type":"directory","name":"2.1.3","size":4096,"contents":[
            {"type":"file","name":"min.html","size":93},
            {"type":"file","name":"min.mod.html","size":46}
          ]},
          {"type":"directory","name":"2.1.4","size":4096,"contents":[
            {"type":"file","name":"min.html","size":93},
            {"type":"file","name":"min.mod.html","size":46}
          ]},
          {"type":"directory","name":"latest","size":4096,"contents":[
            {"type":"file","name":"min.html","size":93},
            {"type":"file","name":"min.mod.html","size":46}
          ]}
        ]}
      ]},
      {"type":"directory","name":"v","size":4096,"contents":[
        {"type":"directory","name":"vue-js","size":4096,"contents":[
          {"type":"directory","name":"2.6.10","size":4096,"contents":[
            {"type":"file","name":"common.dev.html","size":92},
            {"type":"file","name":"common.dev.mod.html","size":46},
            {"type":"file","name":"common.html","size":88},
            {"type":"file","name":"common.mod.html","size":46},
            {"type":"file","name":"common.prod.html","size":93},
            {"type":"file","name":"common.prod.mod.html","size":46},
            {"type":"file","name":"core.html","size":81},
            {"type":"file","name":"core.mod.html","size":46},
            {"type":"file","name":"esm.browser.html","size":93},
            {"type":"file","name":"esm.browser.min.html","size":97},
            {"type":"file","name":"esm.browser.min.mod.html","size":46},
            {"type":"file","name":"esm.browser.mod.html","size":46},
            {"type":"file","name":"esm.html","size":85},
            {"type":"file","name":"esm.mod.html","size":46},
            {"type":"file","name":"min.html","size":85},
            {"type":"file","name":"min.mod.html","size":46},
            {"type":"file","name":"runtime.common.dev.html","size":100},
            {"type":"file","name":"runtime.common.dev.mod.html","size":46},
            {"type":"file","name":"runtime.common.html","size":96},
            {"type":"file","name":"runtime.common.mod.html","size":46},
            {"type":"file","name":"runtime.common.prod.html","size":101},
            {"type":"file","name":"runtime.common.prod.mod.html","size":46},
            {"type":"file","name":"runtime.esm.html","size":93},
            {"type":"file","name":"runtime.esm.mod.html","size":46},
            {"type":"file","name":"runtime.html","size":89},
            {"type":"file","name":"runtime.min.html","size":93},
            {"type":"file","name":"runtime.min.mod.html","size":46},
            {"type":"file","name":"runtime.mod.html","size":46}
          ]},
          {"type":"directory","name":"latest","size":4096,"contents":[
            {"type":"file","name":"common.dev.html","size":92},
            {"type":"file","name":"common.dev.mod.html","size":46},
            {"type":"file","name":"common.html","size":88},
            {"type":"file","name":"common.mod.html","size":46},
            {"type":"file","name":"common.prod.html","size":93},
            {"type":"file","name":"common.prod.mod.html","size":46},
            {"type":"file","name":"core.html","size":81},
            {"type":"file","name":"core.mod.html","size":46},
            {"type":"file","name":"esm.browser.html","size":93},
            {"type":"file","name":"esm.browser.min.html","size":97},
            {"type":"file","name":"esm.browser.min.mod.html","size":46},
            {"type":"file","name":"esm.browser.mod.html","size":46},
            {"type":"file","name":"esm.html","size":85},
            {"type":"file","name":"esm.mod.html","size":46},
            {"type":"file","name":"min.html","size":85},
            {"type":"file","name":"min.mod.html","size":46},
            {"type":"file","name":"runtime.common.dev.html","size":100},
            {"type":"file","name":"runtime.common.dev.mod.html","size":46},
            {"type":"file","name":"runtime.common.html","size":96},
            {"type":"file","name":"runtime.common.mod.html","size":46},
            {"type":"file","name":"runtime.common.prod.html","size":101},
            {"type":"file","name":"runtime.common.prod.mod.html","size":46},
            {"type":"file","name":"runtime.esm.html","size":93},
            {"type":"file","name":"runtime.esm.mod.html","size":46},
            {"type":"file","name":"runtime.html","size":89},
            {"type":"file","name":"runtime.min.html","size":93},
            {"type":"file","name":"runtime.min.mod.html","size":46},
            {"type":"file","name":"runtime.mod.html","size":46}
          ]}
        ]}
      ]},
      {"type":"directory","name":"w","size":4096,"contents":[
        {"type":"directory","name":"waypoints","size":4096,"contents":[
          {"type":"directory","name":"4.0.1","size":4096,"contents":[
            {"type":"file","name":"core.html","size":104},
            {"type":"file","name":"core.mod.html","size":46},
            {"type":"file","name":"debug.html","size":98},
            {"type":"file","name":"debug.mod.html","size":46},
            {"type":"file","name":"infinite.html","size":101},
            {"type":"file","name":"infinite.min.html","size":105},
            {"type":"file","name":"infinite.min.mod.html","size":46},
            {"type":"file","name":"infinite.mod.html","size":46},
            {"type":"file","name":"inview.html","size":99},
            {"type":"file","name":"inview.min.html","size":103},
            {"type":"file","name":"inview.min.mod.html","size":46},
            {"type":"file","name":"inview.mod.html","size":46},
            {"type":"file","name":"jquery.html","size":99},
            {"type":"file","name":"jquery.min.html","size":103},
            {"type":"file","name":"jquery.min.mod.html","size":46},
            {"type":"file","name":"jquery.mod.html","size":46},
            {"type":"file","name":"min.html","size":108},
            {"type":"file","name":"min.mod.html","size":46},
            {"type":"file","name":"sticky.html","size":99},
            {"type":"file","name":"sticky.min.html","size":103},
            {"type":"file","name":"sticky.min.mod.html","size":46},
            {"type":"file","name":"sticky.mod.html","size":46},
            {"type":"file","name":"zepto.html","size":98},
            {"type":"file","name":"zepto.min.html","size":102},
            {"type":"file","name":"zepto.min.mod.html","size":46},
            {"type":"file","name":"zepto.mod.html","size":46}
          ]},
          {"type":"directory","name":"latest","size":4096,"contents":[
            {"type":"file","name":"core.html","size":104},
            {"type":"file","name":"core.mod.html","size":46},
            {"type":"file","name":"debug.html","size":98},
            {"type":"file","name":"debug.mod.html","size":46},
            {"type":"file","name":"infinite.html","size":101},
            {"type":"file","name":"infinite.min.html","size":105},
            {"type":"file","name":"infinite.min.mod.html","size":46},
            {"type":"file","name":"infinite.mod.html","size":46},
            {"type":"file","name":"inview.html","size":99},
            {"type":"file","name":"inview.min.html","size":103},
            {"type":"file","name":"inview.min.mod.html","size":46},
            {"type":"file","name":"inview.mod.html","size":46},
            {"type":"file","name":"jquery.html","size":99},
            {"type":"file","name":"jquery.min.html","size":103},
            {"type":"file","name":"jquery.min.mod.html","size":46},
            {"type":"file","name":"jquery.mod.html","size":46},
            {"type":"file","name":"min.html","size":108},
            {"type":"file","name":"min.mod.html","size":46},
            {"type":"file","name":"sticky.html","size":99},
            {"type":"file","name":"sticky.min.html","size":103},
            {"type":"file","name":"sticky.min.mod.html","size":46},
            {"type":"file","name":"sticky.mod.html","size":46},
            {"type":"file","name":"zepto.html","size":98},
            {"type":"file","name":"zepto.min.html","size":102},
            {"type":"file","name":"zepto.min.mod.html","size":46},
            {"type":"file","name":"zepto.mod.html","size":46}
          ]}
        ]},
        {"type":"directory","name":"wow-js","size":4096,"contents":[
          {"type":"directory","name":"1.1.2","size":4096,"contents":[
            {"type":"file","name":"core.html","size":80},
            {"type":"file","name":"core.mod.html","size":46},
            {"type":"file","name":"min.html","size":84},
            {"type":"file","name":"min.mod.html","size":46}
          ]},
          {"type":"directory","name":"latest","size":4096,"contents":[
            {"type":"file","name":"core.html","size":80},
            {"type":"file","name":"core.mod.html","size":46},
            {"type":"file","name":"min.html","size":84},
            {"type":"file","name":"min.mod.html","size":46}
          ]}
        ]}
      ]},
      {"type":"directory","name":"x","size":4096,"contents":[
        {"type":"directory","name":"xterm-js","size":4096,"contents":[
          {"type":"directory","name":"3.14.5","size":4096,"contents":[
            {"type":"file","name":"attach.html","size":100},
            {"type":"file","name":"attach.min.html","size":104},
            {"type":"file","name":"attach.min.mod.html","size":46},
            {"type":"file","name":"attach.mod.html","size":46},
            {"type":"file","name":"core.html","size":85},
            {"type":"file","name":"core.mod.html","size":46},
            {"type":"file","name":"fit.html","size":94},
            {"type":"file","name":"fit.min.html","size":98},
            {"type":"file","name":"fit.min.mod.html","size":46},
            {"type":"file","name":"fit.mod.html","size":46},
            {"type":"file","name":"fullscreen.html","size":108},
            {"type":"file","name":"fullscreen.min.html","size":112},
            {"type":"file","name":"fullscreen.min.mod.html","size":46},
            {"type":"file","name":"fullscreen.mod.html","size":46},
            {"type":"file","name":"min.html","size":89},
            {"type":"file","name":"min.mod.html","size":46},
            {"type":"file","name":"search.html","size":100},
            {"type":"file","name":"search.min.html","size":104},
            {"type":"file","name":"search.min.mod.html","size":46},
            {"type":"file","name":"search.mod.html","size":46},
            {"type":"file","name":"terminado.html","size":106},
            {"type":"file","name":"terminado.min.html","size":110},
            {"type":"file","name":"terminado.min.mod.html","size":46},
            {"type":"file","name":"terminado.mod.html","size":46},
            {"type":"file","name":"webLinks.html","size":104},
            {"type":"file","name":"webLinks.min.html","size":108},
            {"type":"file","name":"webLinks.min.mod.html","size":46},
            {"type":"file","name":"webLinks.mod.html","size":46},
            {"type":"file","name":"zmodem.html","size":100},
            {"type":"file","name":"zmodem.min.html","size":104},
            {"type":"file","name":"zmodem.min.mod.html","size":46},
            {"type":"file","name":"zmodem.mod.html","size":46}
          ]},
          {"type":"directory","name":"latest","size":4096,"contents":[
            {"type":"file","name":"attach.html","size":100},
            {"type":"file","name":"attach.min.html","size":104},
            {"type":"file","name":"attach.min.mod.html","size":46},
            {"type":"file","name":"attach.mod.html","size":46},
            {"type":"file","name":"core.html","size":85},
            {"type":"file","name":"core.mod.html","size":46},
            {"type":"file","name":"fit.html","size":94},
            {"type":"file","name":"fit.min.html","size":98},
            {"type":"file","name":"fit.min.mod.html","size":46},
            {"type":"file","name":"fit.mod.html","size":46},
            {"type":"file","name":"fullscreen.html","size":108},
            {"type":"file","name":"fullscreen.min.html","size":112},
            {"type":"file","name":"fullscreen.min.mod.html","size":46},
            {"type":"file","name":"fullscreen.mod.html","size":46},
            {"type":"file","name":"min.html","size":89},
            {"type":"file","name":"min.mod.html","size":46},
            {"type":"file","name":"search.html","size":100},
            {"type":"file","name":"search.min.html","size":104},
            {"type":"file","name":"search.min.mod.html","size":46},
            {"type":"file","name":"search.mod.html","size":46},
            {"type":"file","name":"terminado.html","size":106},
            {"type":"file","name":"terminado.min.html","size":110},
            {"type":"file","name":"terminado.min.mod.html","size":46},
            {"type":"file","name":"terminado.mod.html","size":46},
            {"type":"file","name":"webLinks.html","size":104},
            {"type":"file","name":"webLinks.min.html","size":108},
            {"type":"file","name":"webLinks.min.mod.html","size":46},
            {"type":"file","name":"webLinks.mod.html","size":46},
            {"type":"file","name":"zmodem.html","size":100},
            {"type":"file","name":"zmodem.min.html","size":104},
            {"type":"file","name":"zmodem.min.mod.html","size":46},
            {"type":"file","name":"zmodem.mod.html","size":46}
          ]}
        ]}
      ]}
    ]},
    {"type":"file","name":"sources.csv","size":188679},
    {"type":"directory","name":"src","size":4096,"contents":[
      {"type":"directory","name":"b","size":4096,"contents":[
        {"type":"directory","name":"base64-js","size":4096,"contents":[
          {"type":"directory","name":"1.0.2","size":4096,"contents":[
            {"type":"file","name":"core.js","size":2443},
            {"type":"file","name":"min.js","size":870}
          ]},
          {"type":"directory","name":"latest","size":4096,"contents":[
            {"type":"file","name":"core.js","size":2443},
            {"type":"file","name":"min.js","size":870}
          ]}
        ]},
        {"type":"directory","name":"bitcoinjs-lib","size":4096,"contents":[
          {"type":"directory","name":"0.2.0-1","size":4096,"contents":[
            {"type":"file","name":"min.js","size":219198}
          ]},
          {"type":"directory","name":"latest","size":4096,"contents":[
            {"type":"file","name":"min.js","size":219198}
          ]}
        ]},
        {"type":"directory","name":"bootstrap","size":4096,"contents":[
          {"type":"directory","name":"3.0.0","size":4096,"contents":[
            {"type":"file","name":"core.js","size":58458},
            {"type":"file","name":"min.js","size":27726}
          ]},
          {"type":"directory","name":"3.0.1","size":4096,"contents":[
            {"type":"file","name":"core.js","size":58411},
            {"type":"file","name":"min.js","size":27832}
          ]},
          {"type":"directory","name":"3.1.0","size":4096,"contents":[
            {"type":"file","name":"core.js","size":55244},
            {"type":"file","name":"min.js","size":29097}
          ]},
          {"type":"directory","name":"3.3.7","size":4096,"contents":[
            {"type":"file","name":"core.js","size":69707},
            {"type":"file","name":"min.js","size":37045}
          ]},
          {"type":"directory","name":"3.4.1","size":4096,"contents":[
            {"type":"file","name":"core.js","size":75484},
            {"type":"file","name":"min.js","size":39680}
          ]},
          {"type":"directory","name":"4.0.0","size":4096,"contents":[
            {"type":"file","name":"core.js","size":115048},
            {"type":"file","name":"min.js","size":48944}
          ]},
          {"type":"directory","name":"4.1.0","size":4096,"contents":[
            {"type":"file","name":"core.js","size":122441},
            {"type":"file","name":"min.js","size":50676}
          ]},
          {"type":"directory","name":"4.1.1","size":4096,"contents":[
            {"type":"file","name":"core.js","size":122579},
            {"type":"file","name":"min.js","size":50731}
          ]},
          {"type":"directory","name":"4.2.0","size":4096,"contents":[
            {"type":"file","name":"core.js","size":126044},
            {"type":"file","name":"min.js","size":55775}
          ]},
          {"type":"directory","name":"4.2.1","size":4096,"contents":[
            {"type":"file","name":"core.js","size":126044},
            {"type":"file","name":"min.js","size":55775}
          ]},
          {"type":"directory","name":"4.3.0","size":4096,"contents":[
            {"type":"file","name":"core.js","size":127170},
            {"type":"file","name":"min.js","size":56292}
          ]},
          {"type":"directory","name":"4.3.1","size":4096,"contents":[
            {"type":"file","name":"core.js","size":131637},
            {"type":"file","name":"min.js","size":58072}
          ]},
          {"type":"directory","name":"latest","size":4096,"contents":[
            {"type":"file","name":"core.js","size":131637},
            {"type":"file","name":"min.js","size":58072}
          ]}
        ]}
      ]},
      {"type":"directory","name":"c","size":4096,"contents":[
        {"type":"directory","name":"clipboard-js","size":4096,"contents":[
          {"type":"directory","name":"2.0.4","size":4096,"contents":[
            {"type":"file","name":"core.js","size":29276},
            {"type":"file","name":"min.js","size":10754}
          ]},
          {"type":"directory","name":"latest","size":4096,"contents":[
            {"type":"file","name":"core.js","size":29276},
            {"type":"file","name":"min.js","size":10754}
          ]}
        ]},
        {"type":"directory","name":"counterup","size":4096,"contents":[
          {"type":"directory","name":"1.0.0","size":4096,"contents":[
            {"type":"file","name":"core.js","size":2576},
            {"type":"file","name":"min.js","size":1067}
          ]},
          {"type":"directory","name":"latest","size":4096,"contents":[
            {"type":"file","name":"core.js","size":2576},
            {"type":"file","name":"min.js","size":1067}
          ]}
        ]},
        {"type":"directory","name":"crypto-js","size":4096,"contents":[
          {"type":"directory","name":"3.1.9-1","size":4096,"contents":[
            {"type":"file","name":"core.js","size":191936},
            {"type":"file","name":"min.js","size":47943}
          ]},
          {"type":"directory","name":"latest","size":4096,"contents":[
            {"type":"file","name":"core.js","size":191936},
            {"type":"file","name":"min.js","size":47943}
          ]}
        ]}
      ]},
      {"type":"directory","name":"d","size":4096,"contents":[
        {"type":"directory","name":"d3","size":4096,"contents":[
          {"type":"directory","name":"5.11.0","size":4096,"contents":[
            {"type":"file","name":"core.js","size":510262},
            {"type":"file","name":"min.js","size":245526}
          ]},
          {"type":"directory","name":"latest","size":4096,"contents":[
            {"type":"file","name":"core.js","size":510262},
            {"type":"file","name":"min.js","size":245526}
          ]}
        ]},
        {"type":"directory","name":"d3-geo-projection","size":4096,"contents":[
          {"type":"directory","name":"2.4.0","size":4096,"contents":[
            {"type":"file","name":"core.js","size":130846},
            {"type":"file","name":"min.js","size":56561}
          ]},
          {"type":"directory","name":"latest","size":4096,"contents":[
            {"type":"file","name":"core.js","size":130846},
            {"type":"file","name":"min.js","size":56561}
          ]}
        ]},
        {"type":"directory","name":"datatables","size":4096,"contents":[
          {"type":"directory","name":"1.10.19","size":4096,"contents":[
            {"type":"file","name":"bootstrap4.js","size":4693},
            {"type":"file","name":"bootstrap4.min.js","size":2085},
            {"type":"file","name":"bootstrap.js","size":4559},
            {"type":"file","name":"bootstrap.min.js","size":1966},
            {"type":"file","name":"core.js","size":868},
            {"type":"file","name":"foundation.js","size":4373},
            {"type":"file","name":"foundation.min.js","size":2132},
            {"type":"file","name":"jquery.dataTables.js","size":447570},
            {"type":"file","name":"jquery.dataTables.min.js","size":82411},
            {"type":"file","name":"jqueryui.js","size":4486},
            {"type":"file","name":"jqueryui.min.js","size":2647},
            {"type":"file","name":"material.js","size":4789},
            {"type":"file","name":"material.min.js","size":2105},
            {"type":"file","name":"min.js","size":433},
            {"type":"file","name":"semanticui.js","size":5313},
            {"type":"file","name":"semanticui.min.js","size":2444},
            {"type":"file","name":"uikit.js","size":4638},
            {"type":"file","name":"uikit.min.js","size":2269}
          ]},
          {"type":"directory","name":"latest","size":4096,"contents":[
            {"type":"file","name":"bootstrap4.js","size":4693},
            {"type":"file","name":"bootstrap4.min.js","size":2085},
            {"type":"file","name":"bootstrap.js","size":4559},
            {"type":"file","name":"bootstrap.min.js","size":1966},
            {"type":"file","name":"core.js","size":868},
            {"type":"file","name":"foundation.js","size":4373},
            {"type":"file","name":"foundation.min.js","size":2132},
            {"type":"file","name":"jquery.dataTables.js","size":447570},
            {"type":"file","name":"jquery.dataTables.min.js","size":82411},
            {"type":"file","name":"jqueryui.js","size":4486},
            {"type":"file","name":"jqueryui.min.js","size":2647},
            {"type":"file","name":"material.js","size":4789},
            {"type":"file","name":"material.min.js","size":2105},
            {"type":"file","name":"min.js","size":433},
            {"type":"file","name":"semanticui.js","size":5313},
            {"type":"file","name":"semanticui.min.js","size":2444},
            {"type":"file","name":"uikit.js","size":4638},
            {"type":"file","name":"uikit.min.js","size":2269}
          ]}
        ]},
        {"type":"directory","name":"dygraph","size":4096,"contents":[
          {"type":"directory","name":"2.1.0","size":4096,"contents":[
            {"type":"file","name":"core.js","size":399200},
            {"type":"file","name":"min.js","size":123954}
          ]},
          {"type":"directory","name":"latest","size":4096,"contents":[
            {"type":"file","name":"core.js","size":399200},
            {"type":"file","name":"min.js","size":123954}
          ]}
        ]},
        {"type":"directory","name":"dynamics-js","size":4096,"contents":[
          {"type":"directory","name":"1.1.5","size":4096,"contents":[
            {"type":"file","name":"core.js","size":61563},
            {"type":"file","name":"min.js","size":26992}
          ]},
          {"type":"directory","name":"latest","size":4096,"contents":[
            {"type":"file","name":"core.js","size":61563},
            {"type":"file","name":"min.js","size":26992}
          ]}
        ]}
      ]},
      {"type":"file","name":"index.html","size":52925},
      {"type":"directory","name":"j","size":4096,"contents":[
        {"type":"directory","name":"jquery","size":4096,"contents":[
          {"type":"directory","name":"3.3.0","size":4096,"contents":[
            {"type":"file","name":"core.js","size":271751},
            {"type":"file","name":"min.js","size":86927},
            {"type":"file","name":"slim.js","size":218897},
            {"type":"file","name":"slim.min.js","size":69917}
          ]},
          {"type":"directory","name":"3.3.1","size":4096,"contents":[
            {"type":"file","name":"core.js","size":271751},
            {"type":"file","name":"min.js","size":86927},
            {"type":"file","name":"slim.js","size":218897},
            {"type":"file","name":"slim.min.js","size":69917}
          ]},
          {"type":"directory","name":"latest","size":4096,"contents":[
            {"type":"file","name":"core.js","size":271751},
            {"type":"file","name":"min.js","size":86927},
            {"type":"file","name":"slim.js","size":218897},
            {"type":"file","name":"slim.min.js","size":69917}
          ]}
        ]},
        {"type":"directory","name":"jquery-imagesloaded","size":4096,"contents":[
          {"type":"directory","name":"4.1.4","size":4096,"contents":[
            {"type":"file","name":"core.js","size":9965},
            {"type":"file","name":"min.js","size":4442},
            {"type":"file","name":"pkgd.js","size":12786},
            {"type":"file","name":"pkgd.min.js","size":5594}
          ]},
          {"type":"directory","name":"latest","size":4096,"contents":[
            {"type":"file","name":"core.js","size":9965},
            {"type":"file","name":"min.js","size":4442},
            {"type":"file","name":"pkgd.js","size":12786},
            {"type":"file","name":"pkgd.min.js","size":5594}
          ]}
        ]},
        {"type":"directory","name":"jquery-magnific-popup","size":4096,"contents":[
          {"type":"directory","name":"1.1.0","size":4096,"contents":[
            {"type":"file","name":"core.js","size":41730},
            {"type":"file","name":"min.js","size":20216}
          ]},
          {"type":"directory","name":"latest","size":4096,"contents":[
            {"type":"file","name":"core.js","size":41730},
            {"type":"file","name":"min.js","size":20216}
          ]}
        ]},
        {"type":"directory","name":"jquery-metismenu","size":4096,"contents":[
          {"type":"directory","name":"3.0.4","size":4096,"contents":[
            {"type":"file","name":"core.js","size":10326},
            {"type":"file","name":"min.js","size":4786}
          ]},
          {"type":"directory","name":"latest","size":4096,"contents":[
            {"type":"file","name":"core.js","size":10326},
            {"type":"file","name":"min.js","size":4786}
          ]}
        ]},
        {"type":"directory","name":"jquery-slimscroll","size":4096,"contents":[
          {"type":"directory","name":"1.3.8","size":4096,"contents":[
            {"type":"file","name":"core.js","size":13832},
            {"type":"file","name":"min.js","size":4724}
          ]},
          {"type":"directory","name":"latest","size":4096,"contents":[
            {"type":"file","name":"core.js","size":13832},
            {"type":"file","name":"min.js","size":4724}
          ]}
        ]},
        {"type":"directory","name":"jquery-ui","size":4096,"contents":[
          {"type":"directory","name":"1.12.1","size":4096,"contents":[
            {"type":"file","name":"core.js","size":520714},
            {"type":"file","name":"min.js","size":253669}
          ]},
          {"type":"directory","name":"latest","size":4096,"contents":[
            {"type":"file","name":"core.js","size":520714},
            {"type":"file","name":"min.js","size":253669}
          ]}
        ]},
        {"type":"directory","name":"json2html","size":4096,"contents":[
          {"type":"directory","name":"1.3.0","size":4096,"contents":[
            {"type":"file","name":"core.js","size":14582},
            {"type":"file","name":"min.js","size":3855}
          ]},
          {"type":"directory","name":"latest","size":4096,"contents":[
            {"type":"file","name":"core.js","size":14582},
            {"type":"file","name":"min.js","size":3855}
          ]}
        ]},
        {"type":"directory","name":"jszip","size":4096,"contents":[
          {"type":"directory","name":"3.2.2","size":4096,"contents":[
            {"type":"file","name":"core.js","size":366226},
            {"type":"file","name":"min.js","size":95827}
          ]},
          {"type":"directory","name":"latest","size":4096,"contents":[
            {"type":"file","name":"core.js","size":366226},
            {"type":"file","name":"min.js","size":95827}
          ]}
        ]}
      ]},
      {"type":"directory","name":"o","size":4096,"contents":[
        {"type":"directory","name":"openpgp-js","size":4096,"contents":[
          {"type":"directory","name":"4.6.0","size":4096,"contents":[
            {"type":"file","name":"compat.js","size":2000042},
            {"type":"file","name":"compat.min.js","size":790812},
            {"type":"file","name":"compat.worker.js","size":4769},
            {"type":"file","name":"compat.worker.min.js","size":1700},
            {"type":"file","name":"core.js","size":1462441},
            {"type":"file","name":"min.js","size":584530},
            {"type":"file","name":"worker.js","size":4769},
            {"type":"file","name":"worker.min.js","size":1700}
          ]},
          {"type":"directory","name":"latest","size":4096,"contents":[
            {"type":"file","name":"compat.js","size":2000042},
            {"type":"file","name":"compat.min.js","size":790812},
            {"type":"file","name":"compat.worker.js","size":4769},
            {"type":"file","name":"compat.worker.min.js","size":1700},
            {"type":"file","name":"core.js","size":1462441},
            {"type":"file","name":"min.js","size":584530},
            {"type":"file","name":"worker.js","size":4769},
            {"type":"file","name":"worker.min.js","size":1700}
          ]}
        ]}
      ]},
      {"type":"directory","name":"p","size":4096,"contents":[
        {"type":"directory","name":"parallax-js","size":4096,"contents":[
          {"type":"directory","name":"3.1.0","size":4096,"contents":[
            {"type":"file","name":"core.js","size":96610},
            {"type":"file","name":"min.js","size":17314}
          ]},
          {"type":"directory","name":"latest","size":4096,"contents":[
            {"type":"file","name":"core.js","size":96610},
            {"type":"file","name":"min.js","size":17314}
          ]}
        ]},
        {"type":"directory","name":"popper","size":4096,"contents":[
          {"type":"directory","name":"1.14.6","size":4096,"contents":[
            {"type":"file","name":"core.js","size":87009},
            {"type":"file","name":"min.js","size":20973}
          ]},
          {"type":"directory","name":"1.14.7","size":4096,"contents":[
            {"type":"file","name":"core.js","size":87203},
            {"type":"file","name":"min.js","size":21004}
          ]},
          {"type":"directory","name":"latest","size":4096,"contents":[
            {"type":"file","name":"core.js","size":87203},
            {"type":"file","name":"min.js","size":21004}
          ]}
        ]},
        {"type":"directory","name":"pouchdb","size":4096,"contents":[
          {"type":"directory","name":"7.1.1","size":4096,"contents":[
            {"type":"file","name":"core.js","size":348871},
            {"type":"file","name":"min.js","size":125540}
          ]},
          {"type":"directory","name":"latest","size":4096,"contents":[
            {"type":"file","name":"core.js","size":348871},
            {"type":"file","name":"min.js","size":125540}
          ]}
        ]}
      ]},
      {"type":"directory","name":"s","size":4096,"contents":[
        {"type":"directory","name":"sizzle-js","size":4096,"contents":[
          {"type":"directory","name":"2.3.4","size":4096,"contents":[
            {"type":"file","name":"core.js","size":65666},
            {"type":"file","name":"min.js","size":19841}
          ]},
          {"type":"directory","name":"latest","size":4096,"contents":[
            {"type":"file","name":"core.js","size":65666},
            {"type":"file","name":"min.js","size":19841}
          ]}
        ]},
        {"type":"directory","name":"slick","size":4096,"contents":[
          {"type":"directory","name":"1.9.0","size":4096,"contents":[
            {"type":"file","name":"core.js","size":89981},
            {"type":"file","name":"min.js","size":43881}
          ]},
          {"type":"directory","name":"latest","size":4096,"contents":[
            {"type":"file","name":"core.js","size":89981},
            {"type":"file","name":"min.js","size":43881}
          ]}
        ]},
        {"type":"directory","name":"socket-io","size":4096,"contents":[
          {"type":"directory","name":"2.2.0","size":4096,"contents":[
            {"type":"file","name":"core.js","size":62421},
            {"type":"file","name":"dev.js","size":154405},
            {"type":"file","name":"slim.dev.js","size":131504},
            {"type":"file","name":"slim.js","size":53044}
          ]},
          {"type":"directory","name":"latest","size":4096,"contents":[
            {"type":"file","name":"core.js","size":62421},
            {"type":"file","name":"dev.js","size":154405},
            {"type":"file","name":"slim.dev.js","size":131504},
            {"type":"file","name":"slim.js","size":53044}
          ]}
        ]}
      ]},
      {"type":"directory","name":"t","size":4096,"contents":[
        {"type":"directory","name":"three-js","size":4096,"contents":[
          {"type":"directory","name":"108","size":4096,"contents":[
            {"type":"file","name":"core.js","size":1163012},
            {"type":"file","name":"min.js","size":583370},
            {"type":"file","name":"module.js","size":1122023}
          ]},
          {"type":"directory","name":"latest","size":4096,"contents":[
            {"type":"file","name":"core.js","size":1163012},
            {"type":"file","name":"min.js","size":583370},
            {"type":"file","name":"module.js","size":1122023}
          ]}
        ]},
        {"type":"directory","name":"toastr-js","size":4096,"contents":[
          {"type":"directory","name":"2.1.3","size":4096,"contents":[
            {"type":"file","name":"min.js","size":5251}
          ]},
          {"type":"directory","name":"2.1.4","size":4096,"contents":[
            {"type":"file","name":"min.js","size":5251}
          ]},
          {"type":"directory","name":"latest","size":4096,"contents":[
            {"type":"file","name":"min.js","size":5251}
          ]}
        ]}
      ]},
      {"type":"directory","name":"v","size":4096,"contents":[
        {"type":"directory","name":"vue-js","size":4096,"contents":[
          {"type":"directory","name":"2.6.10","size":4096,"contents":[
            {"type":"file","name":"common.dev.js","size":319630},
            {"type":"file","name":"common.js","size":157},
            {"type":"file","name":"common.prod.js","size":93509},
            {"type":"file","name":"core.js","size":341462},
            {"type":"file","name":"esm.browser.js","size":314856},
            {"type":"file","name":"esm.browser.min.js","size":92971},
            {"type":"file","name":"esm.js","size":325727},
            {"type":"file","name":"min.js","size":93675},
            {"type":"file","name":"runtime.common.dev.js","size":222992},
            {"type":"file","name":"runtime.common.js","size":173},
            {"type":"file","name":"runtime.common.prod.js","size":64717},
            {"type":"file","name":"runtime.esm.js","size":227112},
            {"type":"file","name":"runtime.js","size":238426},
            {"type":"file","name":"runtime.min.js","size":64883}
          ]},
          {"type":"directory","name":"latest","size":4096,"contents":[
            {"type":"file","name":"common.dev.js","size":319630},
            {"type":"file","name":"common.js","size":157},
            {"type":"file","name":"common.prod.js","size":93509},
            {"type":"file","name":"core.js","size":341462},
            {"type":"file","name":"esm.browser.js","size":314856},
            {"type":"file","name":"esm.browser.min.js","size":92971},
            {"type":"file","name":"esm.js","size":325727},
            {"type":"file","name":"min.js","size":93675},
            {"type":"file","name":"runtime.common.dev.js","size":222992},
            {"type":"file","name":"runtime.common.js","size":173},
            {"type":"file","name":"runtime.common.prod.js","size":64717},
            {"type":"file","name":"runtime.esm.js","size":227112},
            {"type":"file","name":"runtime.js","size":238426},
            {"type":"file","name":"runtime.min.js","size":64883}
          ]}
        ]}
      ]},
      {"type":"directory","name":"w","size":4096,"contents":[
        {"type":"directory","name":"waypoints","size":4096,"contents":[
          {"type":"directory","name":"4.0.1","size":4096,"contents":[
            {"type":"file","name":"core.js","size":20714},
            {"type":"file","name":"debug.js","size":1413},
            {"type":"file","name":"infinite.js","size":2219},
            {"type":"file","name":"infinite.min.js","size":1460},
            {"type":"file","name":"inview.js","size":2804},
            {"type":"file","name":"inview.min.js","size":1723},
            {"type":"file","name":"jquery.js","size":17548},
            {"type":"file","name":"jquery.min.js","size":8833},
            {"type":"file","name":"min.js","size":10283},
            {"type":"file","name":"sticky.js","size":1902},
            {"type":"file","name":"sticky.min.js","size":1243},
            {"type":"file","name":"zepto.js","size":18819},
            {"type":"file","name":"zepto.min.js","size":9350}
          ]},
          {"type":"directory","name":"latest","size":4096,"contents":[
            {"type":"file","name":"core.js","size":20714},
            {"type":"file","name":"debug.js","size":1413},
            {"type":"file","name":"infinite.js","size":2219},
            {"type":"file","name":"infinite.min.js","size":1460},
            {"type":"file","name":"inview.js","size":2804},
            {"type":"file","name":"inview.min.js","size":1723},
            {"type":"file","name":"jquery.js","size":17548},
            {"type":"file","name":"jquery.min.js","size":8833},
            {"type":"file","name":"min.js","size":10283},
            {"type":"file","name":"sticky.js","size":1902},
            {"type":"file","name":"sticky.min.js","size":1243},
            {"type":"file","name":"zepto.js","size":18819},
            {"type":"file","name":"zepto.min.js","size":9350}
          ]}
        ]},
        {"type":"directory","name":"wow-js","size":4096,"contents":[
          {"type":"directory","name":"1.1.2","size":4096,"contents":[
            {"type":"file","name":"core.js","size":15242},
            {"type":"file","name":"min.js","size":8182}
          ]},
          {"type":"directory","name":"latest","size":4096,"contents":[
            {"type":"file","name":"core.js","size":15242},
            {"type":"file","name":"min.js","size":8182}
          ]}
        ]}
      ]},
      {"type":"directory","name":"x","size":4096,"contents":[
        {"type":"directory","name":"xterm-js","size":4096,"contents":[
          {"type":"directory","name":"3.14.5","size":4096,"contents":[
            {"type":"file","name":"attach.js","size":4565},
            {"type":"file","name":"attach.min.js","size":2217},
            {"type":"file","name":"core.js","size":439111},
            {"type":"file","name":"fit.js","size":2906},
            {"type":"file","name":"fit.min.js","size":1699},
            {"type":"file","name":"fullscreen.js","size":1689},
            {"type":"file","name":"fullscreen.min.js","size":1131},
            {"type":"file","name":"min.js","size":225317},
            {"type":"file","name":"search.js","size":11766},
            {"type":"file","name":"search.min.js","size":5388},
            {"type":"file","name":"terminado.js","size":3561},
            {"type":"file","name":"terminado.min.js","size":1940},
            {"type":"file","name":"webLinks.js","size":2689},
            {"type":"file","name":"webLinks.min.js","size":1367},
            {"type":"file","name":"zmodem.js","size":2338},
            {"type":"file","name":"zmodem.min.js","size":1479}
          ]},
          {"type":"directory","name":"latest","size":4096,"contents":[
            {"type":"file","name":"attach.js","size":4565},
            {"type":"file","name":"attach.min.js","size":2217},
            {"type":"file","name":"core.js","size":439111},
            {"type":"file","name":"fit.js","size":2906},
            {"type":"file","name":"fit.min.js","size":1699},
            {"type":"file","name":"fullscreen.js","size":1689},
            {"type":"file","name":"fullscreen.min.js","size":1131},
            {"type":"file","name":"min.js","size":225317},
            {"type":"file","name":"search.js","size":11766},
            {"type":"file","name":"search.min.js","size":5388},
            {"type":"file","name":"terminado.js","size":3561},
            {"type":"file","name":"terminado.min.js","size":1940},
            {"type":"file","name":"webLinks.js","size":2689},
            {"type":"file","name":"webLinks.min.js","size":1367},
            {"type":"file","name":"zmodem.js","size":2338},
            {"type":"file","name":"zmodem.min.js","size":1479}
          ]}
        ]}
      ]}
    ]},
    {"type":"file","name":"tree.json","size":0}
  ]},
  {"type":"report","directories":244,"files":861}
]
